pymecsim/__init__.py
pymecsim/core.py
pymecsim/input.py
pymecsim/utils.py
pymecsim-1.0.dist-info/LICENSE
pymecsim-1.0.dist-info/METADATA
pymecsim-1.0.dist-info/WHEEL
pymecsim-1.0.dist-info/top_level.txt
pymecsim-1.0.dist-info/RECORD
