Metadata-Version: 2.1
Name: pymecsim
Version: 1.0
Summary: Python Cyclic Voltammetry Simulator
Home-page: UNKNOWN
Author: Kiran Vaddi
Author-email: kiranvad@buffalo.edu
License: MIT
Platform: UNKNOWN
Classifier: Programming Language :: Python :: 3
Classifier: License :: OSI Approved :: MIT License
Classifier: Operating System :: OS Independent
Requires-Python: >=3.6
